pdbg/__init__.py
pdbg_bcit-1.0.2.dist-info/LICENSE
pdbg_bcit-1.0.2.dist-info/METADATA
pdbg_bcit-1.0.2.dist-info/WHEEL
pdbg_bcit-1.0.2.dist-info/top_level.txt
pdbg_bcit-1.0.2.dist-info/RECORD
