Metadata-Version: 2.1
Name: pdbg-bcit
Version: 1.0.2
Summary: A Python debugger for learner which print out all changes.
Home-page: https://github.com/y5bcit/pdbg.py
Author: 
Author-email: 
License: UNKNOWN
Platform: UNKNOWN
Classifier: Programming Language :: Python :: 3
Classifier: License :: OSI Approved :: MIT License
Classifier: Operating System :: OS Independent
